patch1337/patch1337.py
patch1337-0.5.1.dist-info/LICENSE
patch1337-0.5.1.dist-info/METADATA
patch1337-0.5.1.dist-info/WHEEL
patch1337-0.5.1.dist-info/entry_points.txt
patch1337-0.5.1.dist-info/top_level.txt
patch1337-0.5.1.dist-info/RECORD
