Metadata-Version: 2.1
Name: patch1337
Version: 0.5.1
Summary: Patches files using .1337 patch files
Author: OMEGA_RAZER
License: GNU GENERAL PUBLIC LICENSE
Project-URL: Homepage, https://omegarazer.github.io/patch1337
Project-URL: Source, https://github.com/OMEGARAZER/patch1337
Project-URL: Bug Reports, https://github.com/OMEGARAZER/patch1337/issues
Keywords: 1337,patch,nvidia
Classifier: Development Status :: 3 - Alpha
Classifier: Environment :: Console
Classifier: Natural Language :: English
Classifier: Operating System :: OS Independent
Classifier: Programming Language :: Python :: 3
Classifier: Programming Language :: Python :: 3.9
Classifier: Programming Language :: Python :: 3.10
Classifier: Programming Language :: Python :: 3.11
Requires-Python: >=3.9
License-File: LICENSE
Requires-Dist: click (>=8.1.3)
Requires-Dist: loguru (>=0.6.0)
Provides-Extra: dev
Requires-Dist: black (>=23.1.0) ; extra == 'dev'
Requires-Dist: pre-commit (>=3.1.1) ; extra == 'dev'
Requires-Dist: refurb (>=1.14.0) ; extra == 'dev'
Requires-Dist: ruff (>=0.0.255) ; extra == 'dev'
